odoo/addons/website_crm_privacy_policy/README.rst
odoo/addons/website_crm_privacy_policy/__init__.py
odoo/addons/website_crm_privacy_policy/__manifest__.py
odoo/addons/website_crm_privacy_policy/i18n/ca.po
odoo/addons/website_crm_privacy_policy/i18n/de.po
odoo/addons/website_crm_privacy_policy/i18n/el_GR.po
odoo/addons/website_crm_privacy_policy/i18n/es.po
odoo/addons/website_crm_privacy_policy/i18n/fr.po
odoo/addons/website_crm_privacy_policy/i18n/it.po
odoo/addons/website_crm_privacy_policy/i18n/pt_BR.po
odoo/addons/website_crm_privacy_policy/i18n/ru.po
odoo/addons/website_crm_privacy_policy/i18n/sl.po
odoo/addons/website_crm_privacy_policy/i18n/website_crm_privacy_policy.pot
odoo/addons/website_crm_privacy_policy/readme/CONTRIBUTORS.rst
odoo/addons/website_crm_privacy_policy/readme/CREDITS.rst
odoo/addons/website_crm_privacy_policy/readme/DESCRIPTION.rst
odoo/addons/website_crm_privacy_policy/readme/USAGE.rst
odoo/addons/website_crm_privacy_policy/static/description/icon.png
odoo/addons/website_crm_privacy_policy/static/description/index.html
odoo/addons/website_crm_privacy_policy/templates/contactus.xml
odoo_addon_website_crm_privacy_policy-16.0.2.0.0.2.dist-info/METADATA
odoo_addon_website_crm_privacy_policy-16.0.2.0.0.2.dist-info/WHEEL
odoo_addon_website_crm_privacy_policy-16.0.2.0.0.2.dist-info/top_level.txt
odoo_addon_website_crm_privacy_policy-16.0.2.0.0.2.dist-info/RECORD
