Metadata-Version: 2.1
Name: odoo-addon-website-crm-privacy-policy
Version: 16.0.2.0.0.2
Summary: Website CRM privacy policy
Home-page: https://github.com/OCA/website
Author: Trey, Tecnativa, Odoo Community Association (OCA)
Author-email: support@odoo-community.org
License: AGPL-3
Platform: UNKNOWN
Classifier: Programming Language :: Python
Classifier: Framework :: Odoo
Classifier: Framework :: Odoo :: 16.0
Classifier: License :: OSI Approved :: GNU Affero General Public License v3
Requires-Python: >=3.10
Requires-Dist: odoo-addon-website-legal-page <16.1dev,>=16.0dev
Requires-Dist: odoo <16.1dev,>=16.0a
